astrocompute/__init__.py
astrocompute/constants.py
astrocompute/library/__init__.py
astrocompute/library/angle.py
astrocompute/library/coordinate_transform.py
astrocompute/library/mathmatics.py
astrocompute/library/matrix2d.py
astrocompute/library/matrix3d.py
astrocompute/library/point.py
astrocompute/library/polar.py
astrocompute/library/spherical.py
astrocompute/library/vector.py
astrocompute/library/vector2d.py
astrocompute/library/vector3d.py
astrocompute/models/__init__.py
astrocompute/models/point.py
astrocompute/models/polar.py
astrocompute/models/spherical.py
astrocompute/models/vector.py
astrocompute-1.0.3.dist-info/licenses/LICENSE
astrocompute-1.0.3.dist-info/WHEEL
astrocompute-1.0.3.dist-info/METADATA
astrocompute-1.0.3.dist-info/RECORD
