Metadata-Version: 2.4
Name: astrocompute
Version: 1.0.3
Summary: A general purpose package for astronomy calculations.
Keywords: astro,astronomy,package
Author-email: Omar Crosby <omar.crosby@gmail.com>
Maintainer: Omar Crosby
Requires-Python: >=3.13
Classifier: Development Status :: 4 - Beta
Classifier: Environment :: Console
Classifier: Intended Audience :: Developers
Classifier: Natural Language :: English
Classifier: Operating System :: OS Independent
Classifier: Programming Language :: Python :: 3
Classifier: Programming Language :: Python :: 3.13
License-File: LICENSE
Requires-Dist: toml
Requires-Dist: pytest ; extra == "dev"
Requires-Dist: pytest-mock ; extra == "dev"
Requires-Dist: pytest-cov ; extra == "dev"
Requires-Dist: coverage ; extra == "dev"
Requires-Dist: pytest-bdd ; extra == "dev"
Requires-Dist: black ; extra == "dev"
Requires-Dist: flake8 ; extra == "dev"
Requires-Dist: isort ; extra == "dev"
Requires-Dist: mypy ; extra == "dev"
Requires-Dist: pylint ; extra == "dev"
Requires-Dist: radon ; extra == "dev"
Requires-Dist: marimo ; extra == "dev"
Requires-Dist: sphinx ; extra == "dev"
Requires-Dist: sphinx_rtd_theme ; extra == "dev"
Requires-Dist: sphinx-autodoc-typehints ; extra == "dev"
Requires-Dist: sphinx ; extra == "docs"
Requires-Dist: sphinx_rtd_theme ; extra == "docs"
Requires-Dist: sphinx-autodoc-typehints ; extra == "docs"
Project-URL: Homepage, https://github.com/ocrosby/astrocompute
Project-URL: Issues, https://github.com/ocrosby/astrocompute/issues
Provides-Extra: dev
Provides-Extra: docs
